<annotation>
	<folder>images</folder>
	<filename>FS_American_Table_30.jpg</filename>
	<path>E:\yolov5\furniture\train\images\FS_American_Table_30.jpg</path>
	<source>
		<database>Unknown</database>
	</source>
	<size>
		<width>768</width>
		<height>768</height>
		<depth>3</depth>
	</size>
	<segmented>0</segmented>
	<object>
		<name>table</name>
		<pose>Unspecified</pose>
		<truncated>0</truncated>
		<difficult>0</difficult>
		<bndbox>
			<xmin>6</xmin>
			<ymin>228</ymin>
			<xmax>759</xmax>
			<ymax>585</ymax>
		</bndbox>
	</object>
</annotation>
