<annotation>
	<folder>images</folder>
	<filename>FS_Baroque_Chair_19.jpg</filename>
	<path>E:\yolov5\furniture\train\images\FS_Baroque_Chair_19.jpg</path>
	<source>
		<database>Unknown</database>
	</source>
	<size>
		<width>451</width>
		<height>564</height>
		<depth>3</depth>
	</size>
	<segmented>0</segmented>
	<object>
		<name>chair</name>
		<pose>Unspecified</pose>
		<truncated>0</truncated>
		<difficult>0</difficult>
		<bndbox>
			<xmin>52</xmin>
			<ymin>55</ymin>
			<xmax>415</xmax>
			<ymax>539</ymax>
		</bndbox>
	</object>
</annotation>
